{
  "id": 1697,
  "title": "Checking Existence of Edge Length Limited Paths",
  "slug": "checking-existence-of-edge-length-limited-paths",
  "difficulty": "Hard",
  "tags": [],
  "description": "An undirected graph of n nodes is defined by edgeList, where edgeList[i] = [ui, vi, disi] denotes an edge between nodes ui and vi with distance disi. Note that there may be multiple edges between two nodes.\n\nGiven an array queries, where queries[j] = [pj, qj, limitj], your task is to determine for each queries[j] whether there is a path between pj and qj such that each edge on the path has a distance strictly less than limitj .\n\nReturn _a boolean array_ answer_, where_ answer.length == queries.length _and the_ jth _value of_ answer _is_ true _if there is a path for_ queries[j] _is_ true_, and_ false _otherwise_.",
  "examples": [],
  "constraints": [],
  "starterCode": {
    "python": "",
    "javascript": "",
    "java": "",
    "cpp": ""
  },
  "solutionCode": {
    "python": "\n    ```python\nfrom collections import defaultdict, deque\n\ndef distanceLimitedPathsExist(n, edgeList, queries):\n    graph = defaultdict(list)\n\n    for u, v, dis in edgeList:\n        graph[u].append((v, dis))\n        graph[v].append((u, dis))\n\n    answer = [False] * len(queries)\n    for i, (pj, qj, limitj) in enumerate(queries):\n        q = deque([(pj, 0)])\n        visited = [False] * n\n        visited[pj] = True\n\n        while q:\n            curr_node, curr_dist = q.popleft()\n\n            for next_node, next_dist in graph[curr_node]:\n                if curr_dist + next_dist < limitj:\n                    if next_node == qj:\n                        answer[i] = True\n                        break\n                    if not visited[next_node]:\n                        visited[next_node] = True\n                        q.append((next_node, curr_dist + next_dist))\n            if answer[i]:\n                break\n\n    return answer\n```\n    \n    The algorithm first creates a graph representation using adjacency lists. Then, for each query, it performs a modified Breadth-First Search (BFS) starting from the node `pj`. During the BFS, we keep track of the distance travelled so far for each node in the queue. If we find the node `qj` with a distance less than `limitj`, we mark the answer for the current query as `true` and exit the BFS loop. If not, the answer for the current query will be `false`. We repeat this process for all queries and return the result as a boolean array.\n    ",
    "javascript": "\n    ```javascript\nfunction distanceLimitedPathsExist(n, edgeList, queries) {\n    const graph = new Map();\n\n    for (const [u, v, dis] of edgeList) {\n        if (!graph.has(u)) graph.set(u, []);\n        if (!graph.has(v)) graph.set(v, []);\n        graph.get(u).push([v, dis]);\n        graph.get(v).push([u, dis]);\n    }\n\n    const answer = new Array(queries.length).fill(false);\n    for (let i = 0; i < queries.length; i++) {\n        const [pj, qj, limitj] = queries[i];\n\n        const q = [[pj, 0]];\n        const visited = new Array(n).fill(false);\n        visited[pj] = true;\n\n        while (q.length > 0) {\n            const [curr_node, curr_dist] = q.shift();\n\n            for (const [next_node, next_dist] of graph.get(curr_node) || []) {\n                if (curr_dist + next_dist < limitj) {\n                    if (next_node === qj) {\n                        answer[i] = true;\n                        break;\n                    }\n                    if (!visited[next_node]) {\n                        visited[next_node] = true;\n                        q.push([next_node, curr_dist + next_dist]);\n                    }\n                }\n            }\n            if (answer[i]) break;\n        }\n    }\n    return answer;\n}\n```\n    \n    The algorithm first creates a graph representation using adjacency lists. Then, for each query, it performs a modified Breadth-First Search (BFS) starting from the node `pj`. During the BFS, we keep track of the distance travelled so far for each node in the queue. If we find the node `qj` with a distance less than `limitj`, we mark the answer for the current query as `true` and exit the BFS loop. If not, the answer for the current query will be `false`. We repeat this process for all queries and return the result as a boolean array.\n    ",
    "java": "\n    ```java\nimport java.util.*;\n\npublic class Solution {\n    public boolean[] distanceLimitedPathsExist(int n, int[][] edgeList, int[][] queries) {\n        Map<Integer, List<int[]>> graph = new HashMap<>();\n\n        for (int[] edge : edgeList) {\n            graph.putIfAbsent(edge[0], new ArrayList<>());\n            graph.putIfAbsent(edge[1], new ArrayList<>());\n            graph.get(edge[0]).add(new int[]{edge[1], edge[2]});\n            graph.get(edge[1]).add(new int[]{edge[0], edge[2]});\n        }\n\n        boolean[] answer = new boolean[queries.length];\n        for (int i = 0; i < queries.length; i++) {\n            int pj = queries[i][0], qj = queries[i][1], limitj = queries[i][2];\n\n            Queue<int[]> q = new LinkedList<>();\n            q.add(new int[]{pj, 0});\n            boolean[] visited = new boolean[n];\n            visited[pj] = true;\n\n            while (!q.isEmpty()) {\n                int[] curr = q.poll();\n\n                for (int[] next : graph.getOrDefault(curr[0], new ArrayList<>())) {\n                    if (curr[1] + next[1] < limitj) {\n                        if (next[0] == qj) {\n                            answer[i] = true;\n                            break;\n                        }\n                        if (!visited[next[0]]) {\n                            visited[next[0]] = true;\n                            q.add(new int[]{next[0], curr[1] + next[1]});\n                        }\n                    }\n                }\n                if (answer[i]) \n                    break;\n            }\n        }\n        return answer;\n    }\n}\n```\n    \n    The algorithm first creates a graph representation using adjacency lists. Then, for each query, it performs a modified Breadth-First Search (BFS) starting from the node `pj`. During the BFS, we keep track of the distance travelled so far for each node in the queue. If we find the node `qj` with a distance less than `limitj`, we mark the answer for the current query as `true` and exit the BFS loop. If not, the answer for the current query will be `false`. We repeat this process for all queries and return the result as a boolean array.\n    ",
    "cpp": ""
  },
  "testCases": [],
  "acceptanceRate": 0
}
