{
  "id": 1882,
  "title": "Process Tasks Using Servers",
  "slug": "process-tasks-using-servers",
  "difficulty": "Medium",
  "tags": [],
  "description": "You are given two 0-indexed integer arrays servers and tasks of lengths n​​​​​​ and m​​​​​​ respectively. servers[i] is the weight of the i​​​​​​th​​​​ server, and tasks[j] is the time needed to process the j​​​​​​th​​​​ task in seconds.\n\nTasks are assigned to the servers using a task queue. Initially, all servers are free, and the queue is empty.\n\nAt second j, the jth task is inserted into the queue (starting with the 0th task being inserted at second 0). As long as there are free servers and the queue is not empty, the task in the front of the queue will be assigned to a free server with the smallest weight, and in case of a tie, it is assigned to a free server with the smallest index.\n\nIf there are no free servers and the queue is not empty, we wait until a server becomes free and immediately assign the next task. If multiple servers become free at the same time, then multiple tasks from the queue will be assigned in order of insertion following the weight and index priorities above.\n\nA server that is assigned task j at second t will be free again at second t + tasks[j].\n\nBuild an array ans​​​​ of length m, where ans[j] is the index of the server the j​​​​​​th task will be assigned to.\n\nReturn _the array_ ans​​​​.",
  "examples": [],
  "constraints": [],
  "starterCode": {
    "python": "",
    "javascript": "",
    "java": "",
    "cpp": ""
  },
  "solutionCode": {
    "python": "\n    ```python\nimport heapq\nfrom typing import List\n\ndef assignTasks(servers: List[int], tasks: List[int]) -> List[int]:\n    free_servers = [(servers[i], i) for i in range(len(servers))]\n    heapq.heapify(free_servers)\n    busy_servers = []\n    result = [0] * len(tasks)\n\n    for time in range(len(tasks)):\n        while busy_servers and busy_servers[0][0] <= time:\n            _, server_elem = heapq.heappop(busy_servers)\n            heapq.heappush(free_servers, server_elem)\n        \n        if free_servers:\n            server_elem = heapq.heappop(free_servers)\n            result[time] = server_elem[1]\n            heapq.heappush(busy_servers, (time + tasks[time], server_elem))\n\n    return result\n```\n\n    \n    The algorithm implemented for each programming languages follows the same logic described below:\n\n1. Create two priority queues called `free_servers` and `busy_servers`. The `free_servers` priority queue will store the free servers following the minimum weight and index order. The `busy_servers` priority queue will store the busy servers following the order of their release time.\n2. Add all servers to the `free_servers` priority queue.\n3. Iterate through the tasks array using a variable `t` representing the time step.\n4. For each time step `t`, check if there is any server in `busy_servers` that became free (i.e., its release time equals the current time step `t`). If there is any, remove it from `busy_servers` and add it back to the `free_servers` queue.\n5. If at the current time step `t` there is a task and there is any free server in the `free_servers` queue, assign the task to the smallest free server and add it to the `busy_servers` queue with the updated release time (`t + tasks[i]`, where `i` is the current task index).\n6. Continue the loop until all tasks are assigned.\n\nTime complexity: O(n * log(n) + m * log(n)) - At most we are sorting and looping through each server and task in the algorithm.\nSpace complexity: O(n + m) - We are storing free and busy servers, which have a space complexity proportional to n and the result array which has space complexity proportional to m.\n    ",
    "javascript": "\n    ```javascript\nfunction assignTasks(servers, tasks) {\n    const result = new Array(tasks.length);\n    const freeServers = [];\n    for (let i = 0; i < servers.length; i++) {\n        freeServers.push([servers[i], i]);\n    }\n    freeServers.sort((a, b) => a[0] - b[0] || a[1] - b[1]);\n    const busyServers = [];\n\n    let time = 0;\n    let taskIndex = 0;\n\n    while (taskIndex < tasks.length) {\n        while (busyServers.length && busyServers[0][0] <= time) {\n            const server = busyServers.shift()[1];\n            freeServers.push(server);\n            freeServers.sort((a, b) => a[0] - b[0] || a[1] - b[1]);\n        }\n\n        while (freeServers.length && taskIndex <= time && taskIndex < tasks.length) {\n            const server = freeServers.shift();\n            result[taskIndex] = server[1];\n            busyServers.push([time + tasks[taskIndex], server]);\n            busyServers.sort((a, b) => a[0] - b[0] || a[1][1] - b[1][1]);\n            taskIndex++;\n        }\n\n        time++;\n    }\n\n    return result;\n}\n```\n\n    \n    The algorithm implemented for each programming languages follows the same logic described below:\n\n1. Create two priority queues called `free_servers` and `busy_servers`. The `free_servers` priority queue will store the free servers following the minimum weight and index order. The `busy_servers` priority queue will store the busy servers following the order of their release time.\n2. Add all servers to the `free_servers` priority queue.\n3. Iterate through the tasks array using a variable `t` representing the time step.\n4. For each time step `t`, check if there is any server in `busy_servers` that became free (i.e., its release time equals the current time step `t`). If there is any, remove it from `busy_servers` and add it back to the `free_servers` queue.\n5. If at the current time step `t` there is a task and there is any free server in the `free_servers` queue, assign the task to the smallest free server and add it to the `busy_servers` queue with the updated release time (`t + tasks[i]`, where `i` is the current task index).\n6. Continue the loop until all tasks are assigned.\n\nTime complexity: O(n * log(n) + m * log(n)) - At most we are sorting and looping through each server and task in the algorithm.\nSpace complexity: O(n + m) - We are storing free and busy servers, which have a space complexity proportional to n and the result array which has space complexity proportional to m.\n    ",
    "java": "\n    ```java\nimport java.util.*;\n\npublic int[] assignTasks(int[] servers, int[] tasks) {\n    int[] result = new int[tasks.length];\n    PriorityQueue<int[]> freeServers = new PriorityQueue<>((a, b) -> a[0] != b[0] ? a[0] - b[0] : a[1] - b[1]);\n    PriorityQueue<int[]> busyServers = new PriorityQueue<>(Comparator.comparingInt(a -> a[0]));\n    \n    for (int i = 0; i < servers.length; i++) {\n        freeServers.offer(new int[] {servers[i], i});\n    }\n    \n    int time = 0;\n    int taskIndex = 0;\n    \n    while (taskIndex < tasks.length) {\n        while (!busyServers.isEmpty() && busyServers.peek()[0] <= time) {\n            freeServers.offer(busyServers.poll());\n        }\n        \n        while (!freeServers.isEmpty() && taskIndex <= time && taskIndex < tasks.length) {\n            int[] server = freeServers.poll();\n            result[taskIndex] = server[1];\n            busyServers.offer(new int[] {time + tasks[taskIndex], server[0], server[1]});\n            taskIndex++;\n        }\n        \n        time++;\n    }\n    \n    return result;\n}\n```\n\n    \n    The algorithm implemented for each programming languages follows the same logic described below:\n\n1. Create two priority queues called `free_servers` and `busy_servers`. The `free_servers` priority queue will store the free servers following the minimum weight and index order. The `busy_servers` priority queue will store the busy servers following the order of their release time.\n2. Add all servers to the `free_servers` priority queue.\n3. Iterate through the tasks array using a variable `t` representing the time step.\n4. For each time step `t`, check if there is any server in `busy_servers` that became free (i.e., its release time equals the current time step `t`). If there is any, remove it from `busy_servers` and add it back to the `free_servers` queue.\n5. If at the current time step `t` there is a task and there is any free server in the `free_servers` queue, assign the task to the smallest free server and add it to the `busy_servers` queue with the updated release time (`t + tasks[i]`, where `i` is the current task index).\n6. Continue the loop until all tasks are assigned.\n\nTime complexity: O(n * log(n) + m * log(n)) - At most we are sorting and looping through each server and task in the algorithm.\nSpace complexity: O(n + m) - We are storing free and busy servers, which have a space complexity proportional to n and the result array which has space complexity proportional to m.\n    ",
    "cpp": ""
  },
  "testCases": [],
  "acceptanceRate": 0
}
