{
  "id": 638,
  "title": "Shopping Offers",
  "slug": "shopping-offers",
  "difficulty": "Medium",
  "tags": [],
  "description": "In LeetCode Store, there are n items to sell. Each item has a price. However, there are some special offers, and a special offer consists of one or more different kinds of items with a sale price.\n\nYou are given an integer array price where price[i] is the price of the ith item, and an integer array needs where needs[i] is the number of pieces of the ith item you want to buy.\n\nYou are also given an array special where special[i] is of size n + 1 where special[i][j] is the number of pieces of the jth item in the ith offer and special[i][n] (i.e., the last integer in the array) is the price of the ith offer.\n\nReturn _the lowest price you have to pay for exactly certain items as given, where you could make optimal use of the special offers_. You are not allowed to buy more items than you want, even if that would lower the overall price. You could use any of the special offers as many times as you want.",
  "examples": [],
  "constraints": [],
  "starterCode": {
    "python": "",
    "javascript": "",
    "java": "",
    "cpp": ""
  },
  "solutionCode": {
    "python": "\n    ```python\nfrom typing import List\n\ndef shoppingOffers(price: List[int], special: List[List[int]], needs: List[int]) -> int:\n    def helper(index):\n        if index == len(special):\n            return sum(needs[i] * price[i] for i in range(len(needs)))\n\n        no_offer = helper(index + 1)\n        can_apply_offer = True\n        for i in range(len(needs)):\n            needs[i] -= special[index][i]\n            if needs[i] < 0:\n                can_apply_offer = False\n\n        with_offer = float('inf')\n        if can_apply_offer:\n            offer_cost = special[index][-1] + helper(index)\n            with_offer = min(no_offer, offer_cost)\n\n        for i in range(len(needs)):\n            needs[i] += special[index][i]\n        \n        return with_offer if can_apply_offer else no_offer\n\n    return helper(0)\n```\n\n    \n    The algorithm uses backtracking to solve the problem. We go through each special offer and recursively compute the cost of applying or not applying the offer. When no more offers are available, we compute the cost of buying the remaining items at their regular price.\n\nWe first define a helper function that takes the index of the current special offer as its argument:\n\n1. If the index equals the number of special offers, this means that we have checked all special offers, and we should calculate the cost of buying the remaining items at their regular price. We return the sum of the price multiplied by the required number of items for each item.\n\n2. Calculate the cost of not applying the current special offer by calling the helper function recursively with the next special offer.\n\n3. Check if we can apply the current special offer. To do this, we subtract the number of items in the special offer from the required number of items. If any value in the `needs` array becomes negative, this means that the current special offer does not satisfy the shopping requirements, and we cannot apply it.\n\n4. If the current special offer is applicable, we calculate the cost of applying it by adding the cost of the offer to the cost of applying the subsequent special offers. We then calculate the minimum cost between applying and not applying the current special offer.\n\n5. Update the `needs` array by adding the number of items in the special offer to the required number of items. This is necessary because we subtracted these values earlier when checking if we could apply the offer.\n\n6. If we can apply the current special offer, return the minimum cost between applying and not applying it. Otherwise, return the cost of not applying it.\n\nFinally, we call the helper function with the initial value of 0 to solve the problem from the first special offer.\n    ",
    "javascript": "\n    ```javascript\nfunction shoppingOffers(price, special, needs) {\n    function helper(index) {\n        if (index === special.length) {\n            return needs.reduce((sum, curr, i) => sum + curr * price[i], 0);\n        }\n\n        let no_offer = helper(index + 1);\n        let can_apply_offer = true;\n        for (let i = 0; i < needs.length; ++i) {\n            needs[i] -= special[index][i];\n            if (needs[i] < 0) can_apply_offer = false;\n        }\n\n        let with_offer = Infinity;\n        if (can_apply_offer) {\n            let offer_cost = special[index][needs.length] + helper(index);\n            with_offer = Math.min(no_offer, offer_cost);\n        }\n\n        for (let i = 0; i < needs.length; ++i) {\n            needs[i] += special[index][i];\n        }\n\n        return can_apply_offer ? with_offer : no_offer;\n    }\n\n    return helper(0);\n}\n```\n\n    \n    The algorithm uses backtracking to solve the problem. We go through each special offer and recursively compute the cost of applying or not applying the offer. When no more offers are available, we compute the cost of buying the remaining items at their regular price.\n\nWe first define a helper function that takes the index of the current special offer as its argument:\n\n1. If the index equals the number of special offers, this means that we have checked all special offers, and we should calculate the cost of buying the remaining items at their regular price. We return the sum of the price multiplied by the required number of items for each item.\n\n2. Calculate the cost of not applying the current special offer by calling the helper function recursively with the next special offer.\n\n3. Check if we can apply the current special offer. To do this, we subtract the number of items in the special offer from the required number of items. If any value in the `needs` array becomes negative, this means that the current special offer does not satisfy the shopping requirements, and we cannot apply it.\n\n4. If the current special offer is applicable, we calculate the cost of applying it by adding the cost of the offer to the cost of applying the subsequent special offers. We then calculate the minimum cost between applying and not applying the current special offer.\n\n5. Update the `needs` array by adding the number of items in the special offer to the required number of items. This is necessary because we subtracted these values earlier when checking if we could apply the offer.\n\n6. If we can apply the current special offer, return the minimum cost between applying and not applying it. Otherwise, return the cost of not applying it.\n\nFinally, we call the helper function with the initial value of 0 to solve the problem from the first special offer.\n    ",
    "java": "\n    ```java\nimport java.util.List;\nimport java.util.ArrayList;\n\npublic int shoppingOffers(List<Integer> price, List<List<Integer>> special, List<Integer> needs) {\n    return shoppingOffersHelper(price, special, needs, 0);\n}\n\nprivate int shoppingOffersHelper(List<Integer> price, List<List<Integer>> special, List<Integer> needs, int index) {\n    if (index == special.size()) {\n        int sum = 0;\n        for (int i = 0; i < needs.size(); ++i) {\n            sum += price.get(i) * needs.get(i);\n        }\n        return sum;\n    }\n\n    int no_offer = shoppingOffersHelper(price, special, needs, index + 1);\n    boolean can_apply_offer = true;\n    for (int i = 0; i < needs.size(); ++i) {\n        needs.set(i, needs.get(i) - special.get(index).get(i));\n        if (needs.get(i) < 0) can_apply_offer = false;\n    }\n\n    int with_offer = Integer.MAX_VALUE;\n    if (can_apply_offer) {\n        int offer_cost = special.get(index).get(needs.size()) + shoppingOffersHelper(price, special, needs, index);\n        with_offer = Math.min(no_offer, offer_cost);\n    }\n\n    for (int i = 0; i < needs.size(); ++i) {\n        needs.set(i, needs.get(i) + special.get(index).get(i));\n    }\n\n    return can_apply_offer ? with_offer : no_offer;\n}\n```\n\n    \n    The algorithm uses backtracking to solve the problem. We go through each special offer and recursively compute the cost of applying or not applying the offer. When no more offers are available, we compute the cost of buying the remaining items at their regular price.\n\nWe first define a helper function that takes the index of the current special offer as its argument:\n\n1. If the index equals the number of special offers, this means that we have checked all special offers, and we should calculate the cost of buying the remaining items at their regular price. We return the sum of the price multiplied by the required number of items for each item.\n\n2. Calculate the cost of not applying the current special offer by calling the helper function recursively with the next special offer.\n\n3. Check if we can apply the current special offer. To do this, we subtract the number of items in the special offer from the required number of items. If any value in the `needs` array becomes negative, this means that the current special offer does not satisfy the shopping requirements, and we cannot apply it.\n\n4. If the current special offer is applicable, we calculate the cost of applying it by adding the cost of the offer to the cost of applying the subsequent special offers. We then calculate the minimum cost between applying and not applying the current special offer.\n\n5. Update the `needs` array by adding the number of items in the special offer to the required number of items. This is necessary because we subtracted these values earlier when checking if we could apply the offer.\n\n6. If we can apply the current special offer, return the minimum cost between applying and not applying it. Otherwise, return the cost of not applying it.\n\nFinally, we call the helper function with the initial value of 0 to solve the problem from the first special offer.\n    ",
    "cpp": ""
  },
  "testCases": [],
  "acceptanceRate": 0
}
