{
  "id": 1406,
  "title": "Stone Game III",
  "slug": "stone-game-iii",
  "difficulty": "Hard",
  "tags": [],
  "description": "Alice and Bob continue their games with piles of stones. There are several stones arranged in a row, and each stone has an associated value which is an integer given in the array stoneValue.\n\nAlice and Bob take turns, with Alice starting first. On each player's turn, that player can take 1, 2, or 3 stones from the first remaining stones in the row.\n\nThe score of each player is the sum of the values of the stones taken. The score of each player is 0 initially.\n\nThe objective of the game is to end with the highest score, and the winner is the player with the highest score and there could be a tie. The game continues until all the stones have been taken.\n\nAssume Alice and Bob play optimally.\n\nReturn \"Alice \" _if Alice will win,_ \"Bob \" _if Bob will win, or_ \"Tie \" _if they will end the game with the same score_.",
  "examples": [],
  "constraints": [],
  "starterCode": {
    "python": "",
    "javascript": "",
    "java": "",
    "cpp": ""
  },
  "solutionCode": {
    "python": "\n    ```python\ndef stoneGameIII(stoneValue):\n    n = len(stoneValue)\n    dp = [float(\"-inf\")] * (n + 1)\n    dp[n] = 0\n    \n    for i in range(n - 1, -1, -1):\n        curr = 0\n        for j in range(3):\n            if i + j < n:\n                curr += stoneValue[i + j]\n                dp[i] = max(dp[i], curr - dp[i + j + 1])\n                \n    return \"Tie \" if dp[0] == 0 else \"Alice \" if dp[0] > 0 else \"Bob \"\n```\n\n    \n    We can solve this problem using dynamic programming. Create a `dp` array of size `n+1` where `n` is the length of the stoneValue array, and initialize it with the minimum possible integer value (in Python, use `-inf`). The last element of the `dp` array should be initialized to 0.\nThe idea is to find the maximum score difference each player can achieve, starting from index i, for 0 ≤ i < n. \n\nFor each index i, we calculate the current score (sum of values at most 3 consecutive stones starting from i) and update the `dp[i]` to max(`dp[i]`, current - `dp[i+j+1]`). \n\nAt the end, `dp[0]` represents the maximum score difference between Alice and Bob. If `dp[0] > 0`, Alice wins, if `dp[0] < 0`, Bob wins, and if `dp[0] == 0`, it's a tie.\n    ",
    "javascript": "\n    ```javascript\nvar stoneGameIII = function(stoneValue) {\n    let n = stoneValue.length;\n    let dp = new Array(n + 1).fill(Number.MIN_SAFE_INTEGER);\n    dp[n] = 0;\n    \n    for (let i = n - 1; i >= 0; --i) {\n        let curr = 0;\n        for (let j = 0; j < 3 && i + j < n; ++j) {\n            curr += stoneValue[i + j];\n            dp[i] = Math.max(dp[i], curr - dp[i + j + 1]);\n        }\n    }\n    \n    return dp[0] === 0 ? \"Tie \" : dp[0] > 0 ? \"Alice \" : \"Bob \";\n};\n```\n\n    \n    We can solve this problem using dynamic programming. Create a `dp` array of size `n+1` where `n` is the length of the stoneValue array, and initialize it with the minimum possible integer value (in Python, use `-inf`). The last element of the `dp` array should be initialized to 0.\nThe idea is to find the maximum score difference each player can achieve, starting from index i, for 0 ≤ i < n. \n\nFor each index i, we calculate the current score (sum of values at most 3 consecutive stones starting from i) and update the `dp[i]` to max(`dp[i]`, current - `dp[i+j+1]`). \n\nAt the end, `dp[0]` represents the maximum score difference between Alice and Bob. If `dp[0] > 0`, Alice wins, if `dp[0] < 0`, Bob wins, and if `dp[0] == 0`, it's a tie.\n    ",
    "java": "\n    ```java\npublic String stoneGameIII(int[] stoneValue) {\n    int n = stoneValue.length;\n    int[] dp = new int[n + 1];\n    dp[n] = 0;\n    \n    for (int i = n - 1; i >= 0; --i) {\n        dp[i] = Integer.MIN_VALUE;\n        int curr = 0;\n        for (int j = 0; j < 3 && i + j < n; ++j) {\n            curr += stoneValue[i + j];\n            dp[i] = Math.max(dp[i], curr - dp[i + j + 1]);\n        }\n    }\n    \n    return dp[0] == 0 ? \"Tie \" : dp[0] > 0 ? \"Alice \" : \"Bob \";\n}\n```\n\n    \n    We can solve this problem using dynamic programming. Create a `dp` array of size `n+1` where `n` is the length of the stoneValue array, and initialize it with the minimum possible integer value (in Python, use `-inf`). The last element of the `dp` array should be initialized to 0.\nThe idea is to find the maximum score difference each player can achieve, starting from index i, for 0 ≤ i < n. \n\nFor each index i, we calculate the current score (sum of values at most 3 consecutive stones starting from i) and update the `dp[i]` to max(`dp[i]`, current - `dp[i+j+1]`). \n\nAt the end, `dp[0]` represents the maximum score difference between Alice and Bob. If `dp[0] > 0`, Alice wins, if `dp[0] < 0`, Bob wins, and if `dp[0] == 0`, it's a tie.\n    ",
    "cpp": ""
  },
  "testCases": [],
  "acceptanceRate": 0
}
