{
  "id": 1230,
  "title": "Toss Strange Coins",
  "slug": "toss-strange-coins",
  "difficulty": "Medium",
  "tags": [],
  "description": "You have some coins. The i\\-th coin has a probability prob[i] of facing heads when tossed.\n\nReturn the probability that the number of coins facing heads equals target if you toss every coin exactly once.",
  "examples": [],
  "constraints": [],
  "starterCode": {
    "python": "",
    "javascript": "",
    "java": "",
    "cpp": ""
  },
  "solutionCode": {
    "python": "\n    ```python\ndef max_value(arr1, arr2):\n    n = len(arr1)\n    max1 = max2 = max3 = max4 = float('-inf')\n    min1 = min2 = min3 = min4 = float('inf')\n\n    for i in range(n):\n        max1 = max(max1, arr1[i] - arr2[i] + i)\n        max2 = max(max2, arr1[i] + arr2[i] + i)\n        max3 = max(max3, -arr1[i] + arr2[i] + i)\n        max4 = max(max4, -arr1[i] - arr2[i] + i)\n\n        min1 = min(min1, arr1[i] - arr2[i] + i)\n        min2 = min(min2, arr1[i] + arr2[i] + i)\n        min3 = min(min3, -arr1[i] + arr2[i] + i)\n        min4 = min(min4, -arr1[i] - arr2[i] + i)\n\n    return max(max1 - min1, max2 - min2, max3 - min3, max4 - min4)\n```\n\n    \n    The algorithm first initializes four maximum and four minimum values with appropriate maximum and minimum integer values for the specific programming language. \n\nFor each i in [0, arr1.length), the algorithm calculates the maximum and minimum values for the four possibilities of the expression, i.e.,\n1. arr1[i] - arr2[i] + i\n2. arr1[i] + arr2[i] + i\n3. -arr1[i] + arr2[i] + i\n4. -arr1[i] - arr2[i] + i\n\nAt the end of the loop, the algorithm returns the maximum value of the differences between each maximum value and its corresponding minimum value.\n\nThis approach ensures that the maximum value of the given expression is found efficiently in O(n) time complexity.\n    ",
    "javascript": "\n    ```javascript\nfunction maxValue(arr1, arr2) {\n    let max1 = -Infinity, max2 = -Infinity, max3 = -Infinity, max4 = -Infinity;\n    let min1 = Infinity, min2 = Infinity, min3 = Infinity, min4 = Infinity;\n    let n = arr1.length;\n\n    for (let i = 0; i < n; i++) {\n        max1 = Math.max(max1, arr1[i] - arr2[i] + i);\n        max2 = Math.max(max2, arr1[i] + arr2[i] + i);\n        max3 = Math.max(max3, -arr1[i] + arr2[i] + i);\n        max4 = Math.max(max4, -arr1[i] - arr2[i] + i);\n\n        min1 = Math.min(min1, arr1[i] - arr2[i] + i);\n        min2 = Math.min(min2, arr1[i] + arr2[i] + i);\n        min3 = Math.min(min3, -arr1[i] + arr2[i] + i);\n        min4 = Math.min(min4, -arr1[i] - arr2[i] + i);\n    }\n    return Math.max(Math.max(max1 - min1, max2 - min2),\n            Math.max(max3 - min3, max4 - min4));\n}\n```\n\n    \n    The algorithm first initializes four maximum and four minimum values with appropriate maximum and minimum integer values for the specific programming language. \n\nFor each i in [0, arr1.length), the algorithm calculates the maximum and minimum values for the four possibilities of the expression, i.e.,\n1. arr1[i] - arr2[i] + i\n2. arr1[i] + arr2[i] + i\n3. -arr1[i] + arr2[i] + i\n4. -arr1[i] - arr2[i] + i\n\nAt the end of the loop, the algorithm returns the maximum value of the differences between each maximum value and its corresponding minimum value.\n\nThis approach ensures that the maximum value of the given expression is found efficiently in O(n) time complexity.\n    ",
    "java": "\n    ```java\npublic int maxValue(int[] arr1, int[] arr2) {\n    int max1 = Integer.MIN_VALUE, max2 = Integer.MIN_VALUE,\n        max3 = Integer.MIN_VALUE, max4 = Integer.MIN_VALUE;\n    int min1 = Integer.MAX_VALUE, min2 = Integer.MAX_VALUE,\n        min3 = Integer.MAX_VALUE, min4 = Integer.MAX_VALUE;\n    int n = arr1.length;\n\n    for (int i = 0; i < n; i++) {\n        max1 = Math.max(max1, arr1[i] - arr2[i] + i);\n        max2 = Math.max(max2, arr1[i] + arr2[i] + i);\n        max3 = Math.max(max3, -arr1[i] + arr2[i] + i);\n        max4 = Math.max(max4, -arr1[i] - arr2[i] + i);\n\n        min1 = Math.min(min1, arr1[i] - arr2[i] + i);\n        min2 = Math.min(min2, arr1[i] + arr2[i] + i);\n        min3 = Math.min(min3, -arr1[i] + arr2[i] + i);\n        min4 = Math.min(min4, -arr1[i] - arr2[i] + i);\n    }\n    return Math.max(Math.max(max1 - min1, max2 - min2),\n            Math.max(max3 - min3, max4 - min4));\n}\n```\n\n    \n    The algorithm first initializes four maximum and four minimum values with appropriate maximum and minimum integer values for the specific programming language. \n\nFor each i in [0, arr1.length), the algorithm calculates the maximum and minimum values for the four possibilities of the expression, i.e.,\n1. arr1[i] - arr2[i] + i\n2. arr1[i] + arr2[i] + i\n3. -arr1[i] + arr2[i] + i\n4. -arr1[i] - arr2[i] + i\n\nAt the end of the loop, the algorithm returns the maximum value of the differences between each maximum value and its corresponding minimum value.\n\nThis approach ensures that the maximum value of the given expression is found efficiently in O(n) time complexity.\n    ",
    "cpp": ""
  },
  "testCases": [],
  "acceptanceRate": 0
}
